BookCut-1.3.7.dist-info/DESCRIPTION.rst
BookCut-1.3.7.dist-info/METADATA
BookCut-1.3.7.dist-info/RECORD
BookCut-1.3.7.dist-info/WHEEL
BookCut-1.3.7.dist-info/entry_points.txt
BookCut-1.3.7.dist-info/metadata.json
BookCut-1.3.7.dist-info/top_level.txt
bookcut/Settings.ini
bookcut/__init__.py
bookcut/article.py
bookcut/bibliography.py
bookcut/book.py
bookcut/book_details.py
bookcut/bookcut.py
bookcut/booklist.py
bookcut/downloader.py
bookcut/libgen.py
bookcut/mirror_checker.py
bookcut/organise.py
bookcut/repositories.py
bookcut/search.py
bookcut/settings.py
tests/__init__.py
tests/test_book.py
tests/test_bookcut.py
tests/test_main.py
tests/test_mirror_checker.py
