Metadata-Version: 2.0
Name: BookCut
Version: 1.3.7
Summary: Command Line Interface app to download ebooks.
Home-page: https://github.com/costis94/bookcut
Author: Costis94
Author-email: gravitymusician@gmail.com
License: UNKNOWN
Platform: UNKNOWN
Classifier: Programming Language :: Python :: 3
Classifier: License :: OSI Approved :: MIT License
Classifier: Operating System :: OS Independent
Requires-Python: >3.5.2
Provides-Extra: dev
License-File: LICENSE.txt
Requires-Dist: pandas
Requires-Dist: click (>=7.1.2)
Requires-Dist: requests
Requires-Dist: beautifulsoup4
Requires-Dist: pyfiglet
Requires-Dist: tqdm
Requires-Dist: mechanize
Provides-Extra: dev
Requires-Dist: pytest; extra == 'dev'
Requires-Dist: pytest-cov; extra == 'dev'
Requires-Dist: pre-commit; extra == 'dev'
Requires-Dist: black; extra == 'dev'
